README.md
setup.py
eos_etl.egg-info/PKG-INFO
eos_etl.egg-info/SOURCES.txt
eos_etl.egg-info/dependency_links.txt
eos_etl.egg-info/entry_points.txt
eos_etl.egg-info/requires.txt
eos_etl.egg-info/top_level.txt
eosetl/__init__.py
eosetl/__main__.py
eosetl/cli/__init__.py
eosetl/cli/export_all.py
eosetl/cli/export_blocks.py
eosetl/cli/get_block_range_for_date.py
eosetl/cli/stream.py
eosetl/enumeration/__init__.py
eosetl/jobs/__init__.py
eosetl/jobs/export_all.py
eosetl/jobs/export_blocks_job.py
eosetl/jobs/exporters/__init__.py
eosetl/jobs/exporters/blocks_item_exporter.py
eosetl/mappers/__init__.py
eosetl/mappers/action_mapper.py
eosetl/mappers/block_mapper.py
eosetl/mappers/transaction_mapper.py
eosetl/rpc/__init__.py
eosetl/rpc/eos_rpc.py
eosetl/rpc/request.py
eosetl/service/__init__.py
eosetl/service/eos_block_range_service.py
eosetl/service/eos_block_timestamp_graph.py
eosetl/service/eos_service.py
eosetl/streaming/__init__.py
eosetl/streaming/eos_streamer_adapter.py
tests/eosetl/__init__.py
tests/eosetl/job/__init__.py
tests/eosetl/job/helpers.py
tests/eosetl/job/mock_eos_rpc.py
tests/eosetl/job/test_export_blocks_job.py
tests/eosetl/service/__init__.py
tests/eosetl/service/test_eos_block_range_service.py
tests/resources/__init__.py